sophos_firewall_audit/__init__.py
sophos_firewall_audit/audit.py
sophos_firewall_audit/auth.py
sophos_firewall_audit/images/logo.png
sophos_firewall_audit/logging_config.py
sophos_firewall_audit/remediate.py
sophos_firewall_audit/rule_export.py
sophos_firewall_audit/rules/__init__.py
sophos_firewall_audit/rules/accesslist.py
sophos_firewall_audit/rules/activethreatresponse.py
sophos_firewall_audit/rules/adminauthen.py
sophos_firewall_audit/rules/adminservices.py
sophos_firewall_audit/rules/backup.py
sophos_firewall_audit/rules/central.py
sophos_firewall_audit/rules/certificate.py
sophos_firewall_audit/rules/deviceaccessprofile.py
sophos_firewall_audit/rules/dnsservers.py
sophos_firewall_audit/rules/hostgroups.py
sophos_firewall_audit/rules/ipspolicies.py
sophos_firewall_audit/rules/loginsecurity.py
sophos_firewall_audit/rules/malwareprotection.py
sophos_firewall_audit/rules/notificationlist.py
sophos_firewall_audit/rules/notifications.py
sophos_firewall_audit/rules/smtpprotection.py
sophos_firewall_audit/rules/snmpv3.py
sophos_firewall_audit/rules/syslog.py
sophos_firewall_audit/rules/time.py
sophos_firewall_audit/sophosfirewallaudit.py
sophos_firewall_audit/templates/audit_index.j2
sophos_firewall_audit/templates/email_body.j2
sophos_firewall_audit/templates/home.j2
sophos_firewall_audit/templates/results.j2
sophos_firewall_audit/templates/rules_index.j2
sophos_firewall_audit/utils.py
sophos_firewall_audit-1.0.20.dist-info/METADATA
sophos_firewall_audit-1.0.20.dist-info/WHEEL
sophos_firewall_audit-1.0.20.dist-info/entry_points.txt
sophos_firewall_audit-1.0.20.dist-info/licenses/LICENSE
sophos_firewall_audit-1.0.20.dist-info/RECORD
