Metadata-Version: 2.4
Name: sophos-firewall-audit
Version: 1.0.20
Summary: Sophos Firewall Audit
License-File: LICENSE
Author: Matt Mullen
Author-email: matt.mullen@sophos.com
Requires-Python: >=3.9,<4.0
Classifier: Programming Language :: Python :: 3
Classifier: Programming Language :: Python :: 3.9
Classifier: Programming Language :: Python :: 3.10
Classifier: Programming Language :: Python :: 3.11
Classifier: Programming Language :: Python :: 3.12
Classifier: Programming Language :: Python :: 3.13
Classifier: Programming Language :: Python :: 3.14
Requires-Dist: hvac (>=2.0.0,<3.0.0)
Requires-Dist: jinja2 (>=3.1.2,<4.0.0)
Requires-Dist: packaging (>=23.2,<24.0)
Requires-Dist: prettytable (>=3.9.0,<4.0.0)
Requires-Dist: pynautobot (>=2.0.0,<3.0.0)
Requires-Dist: pyyaml (>=6.0.1,<7.0.0)
Requires-Dist: requests (>=2.31.0,<3.0.0)
Requires-Dist: rich (>=13.5.3,<14.0.0)
Requires-Dist: sophosfirewall-python (>=0.1.36,<0.2.0)
